MANIFEST.in
README.md
requirements.txt
setup.py
flaskweb/__init__.py
flaskweb/app.py
flaskweb/config.py
flaskweb/views.py
flaskweb.egg-info/PKG-INFO
flaskweb.egg-info/SOURCES.txt
flaskweb.egg-info/dependency_links.txt
flaskweb.egg-info/requires.txt
flaskweb.egg-info/top_level.txt
flaskweb/auth/__init__.py
flaskweb/auth/forms.py
flaskweb/auth/models.py
flaskweb/auth/views.py
flaskweb/static/css/vendor/bootstrap.min.css
flaskweb/static/css/vendor/helper.css
flaskweb/static/js/vendor/bootstrap.min.js
flaskweb/static/js/vendor/jquery.min.js
flaskweb/static/public/fonts/glyphicons-halflings-regular.eot
flaskweb/static/public/fonts/glyphicons-halflings-regular.svg
flaskweb/static/public/fonts/glyphicons-halflings-regular.ttf
flaskweb/static/public/fonts/glyphicons-halflings-regular.woff
flaskweb/templates/base.html
flaskweb/templates/debug.html
flaskweb/templates/login.html
flaskweb/templates/register.html