Metadata-Version: 1.0
Name: flaskweb
Version: 0.2.1
Summary: An easy to start yet full-featured web framework
Home-page: UNKNOWN
Author: meteorix
Author-email: lxhustauto@gmail.com
License: UNKNOWN
Platform: UNKNOWN
